LICENSE
MANIFEST.in
README.rst
setup.py
dpprogram/__init__.py
dpprogram/apps.py
dpprogram/urls.py
dpprogram.egg-info/PKG-INFO
dpprogram.egg-info/SOURCES.txt
dpprogram.egg-info/dependency_links.txt
dpprogram.egg-info/requires.txt
dpprogram.egg-info/top_level.txt
dpprogram/admin/Program.py
dpprogram/admin/__init__.py
dpprogram/managers/ProgramManager.py
dpprogram/managers/__init__.py
dpprogram/migrations/0001_initial.py
dpprogram/migrations/0002_auto_20170523_1356.py
dpprogram/migrations/0003_auto_20170524_1212.py
dpprogram/migrations/__init__.py
dpprogram/model_bases/AbstractBaseProgram.py
dpprogram/model_bases/__init__.py
dpprogram/models/Program.py
dpprogram/models/__init__.py
dpprogram/serializers/__init__.py
dpprogram/serializers/program_lc.py
dpprogram/serializers/program_rud.py
dpprogram/signals/__init__.py
dpprogram/signals/handlers.py
dpprogram/views/__init__.py
dpprogram/views/program_lc.py
dpprogram/views/program_rud.py